brk_utils/__init__.py
brk_utils/utils.py
brk-0.0.3.dist-info/LICENSE
brk-0.0.3.dist-info/METADATA
brk-0.0.3.dist-info/WHEEL
brk-0.0.3.dist-info/top_level.txt
brk-0.0.3.dist-info/RECORD
