Metadata-Version: 2.1
Name: brk
Version: 0.0.3
Summary: Utility package for file system and network
Home-page: UNKNOWN
Author: Barkin Kaplan
Author-email: barkinkaplan@example.com
License: UNKNOWN
Platform: UNKNOWN
Classifier: Programming Language :: Python :: 3
Classifier: License :: OSI Approved :: MIT License
Classifier: Operating System :: OS Independent
Requires-Python: >=3.7
